baselines/__init__.py
baselines/cais_baseline.py
baselines/chatbot.py
baselines/coderunner.py
baselines/kernel_http.py
baselines/query_formats.py
baselines/query_generator.py
baselines/run_baselines.py
causal_agent/__init__.py
causal_agent/agent.py
causal_agent/cli.py
causal_agent/config.py
causal_agent/models.py
causal_agent/components/__init__.py
causal_agent/components/dataset_analyzer.py
causal_agent/components/decision_tree.py
causal_agent/components/decision_tree_llm.py
causal_agent/components/explanation_generator.py
causal_agent/components/input_parser.py
causal_agent/components/method_validator.py
causal_agent/components/output_formatter.py
causal_agent/components/query_interpreter.py
causal_agent/components/state_manager.py
causal_agent/methods/__init__.py
causal_agent/methods/causal_method.py
causal_agent/methods/utils.py
causal_agent/methods/backdoor_adjustment/__init__.py
causal_agent/methods/backdoor_adjustment/diagnostics.py
causal_agent/methods/backdoor_adjustment/estimator.py
causal_agent/methods/backdoor_adjustment/llm_assist.py
causal_agent/methods/diff_in_means/__init__.py
causal_agent/methods/diff_in_means/diagnostics.py
causal_agent/methods/diff_in_means/estimator.py
causal_agent/methods/diff_in_means/llm_assist.py
causal_agent/methods/difference_in_differences/diagnostics.py
causal_agent/methods/difference_in_differences/estimator.py
causal_agent/methods/difference_in_differences/llm_assist.py
causal_agent/methods/difference_in_differences/utils.py
causal_agent/methods/generalized_propensity_score/__init__.py
causal_agent/methods/generalized_propensity_score/diagnostics.py
causal_agent/methods/generalized_propensity_score/estimator.py
causal_agent/methods/generalized_propensity_score/llm_assist.py
causal_agent/methods/instrumental_variable/__init__.py
causal_agent/methods/instrumental_variable/diagnostics.py
causal_agent/methods/instrumental_variable/estimator.py
causal_agent/methods/instrumental_variable/llm_assist.py
causal_agent-0.1.2.dist-info/licenses/LICENSE
causal_agent-0.1.2.dist-info/METADATA
causal_agent-0.1.2.dist-info/WHEEL
causal_agent-0.1.2.dist-info/entry_points.txt
causal_agent-0.1.2.dist-info/top_level.txt
causal_agent-0.1.2.dist-info/RECORD
