Metadata-Version: 2.4
Name: causal-agent
Version: 0.1.2
Summary: A library for automated causal inference
Home-page: https://github.com/causalNLP/causal-agent
Author: Vishal Verma
Author-email: Vishal Verma <vishal.verma@andrew.cmu.edu>
License: MIT
Project-URL: Homepage, https://github.com/causalNLP/causal-agent
Project-URL: Issues, https://github.com/causalNLP/causal-agent/issues
Classifier: Development Status :: 3 - Alpha
Classifier: Intended Audience :: Developers
Classifier: Intended Audience :: Science/Research
Classifier: License :: OSI Approved :: MIT License
Classifier: Programming Language :: Python :: 3
Classifier: Programming Language :: Python :: 3.10
Classifier: Operating System :: OS Independent
Classifier: Topic :: Scientific/Engineering :: Artificial Intelligence
Classifier: Topic :: Scientific/Engineering :: Information Analysis
Requires-Python: >=3.10
License-File: LICENSE
Requires-Dist: pandas<3,>=2.1
Requires-Dist: numpy<3,>=1.26
Requires-Dist: scipy<1.15,>=1.10
Requires-Dist: statsmodels<1,>=0.14
Requires-Dist: tqdm<5,>=4.66
Requires-Dist: pydantic<3,>=2.6
Requires-Dist: requests<3,>=2.31
Requires-Dist: python-dotenv<2,>=1
Requires-Dist: langchain-core<0.4,>=0.3
Requires-Dist: langchain-openai<0.4,>=0.3
Requires-Dist: langchain-anthropic<0.4,>=0.3
Requires-Dist: langchain-google-genai<3,>=2
Requires-Dist: langchain-deepseek<0.2,>=0.1
Requires-Dist: langchain-together<0.4,>=0.3
Requires-Dist: langchain<0.4,>=0.3.26
Requires-Dist: seaborn<0.14,>=0.13
Requires-Dist: dowhy<0.13,>=0.12
Provides-Extra: dev
Requires-Dist: pytest<9,>=8; extra == "dev"
Requires-Dist: pytest-cov<5,>=4; extra == "dev"
Requires-Dist: pytest-xdist<4,>=3; extra == "dev"
Requires-Dist: pytest-mock<4,>=3; extra == "dev"
Requires-Dist: pytest-html<5,>=4; extra == "dev"
Requires-Dist: coverage[toml]<8,>=7; extra == "dev"
Requires-Dist: black<25,>=23; extra == "dev"
Requires-Dist: isort<6,>=5; extra == "dev"
Requires-Dist: flake8<8,>=6; extra == "dev"
Requires-Dist: mypy<2,>=1; extra == "dev"
Requires-Dist: pylint<4,>=3; extra == "dev"
Requires-Dist: bandit<2,>=1.7; extra == "dev"
Requires-Dist: safety<4,>=3; extra == "dev"
Requires-Dist: pre-commit<4,>=3; extra == "dev"
Requires-Dist: coverage-badge<2,>=1; extra == "dev"
Provides-Extra: docs
Requires-Dist: sphinx>=7; extra == "docs"
Requires-Dist: myst-parser>=3; extra == "docs"
Requires-Dist: sphinx-rtd-theme>=2; extra == "docs"
Dynamic: author
Dynamic: home-page
Dynamic: license-file
Dynamic: requires-python
